setup.py
stringbuilder/__init__.py
stringbuilder/stringbuilder.py
stringbuilder.py.egg-info/PKG-INFO
stringbuilder.py.egg-info/SOURCES.txt
stringbuilder.py.egg-info/dependency_links.txt
stringbuilder.py.egg-info/requires.txt
stringbuilder.py.egg-info/top_level.txt