Metadata-Version: 2.1
Name: stringbuilder.py
Version: 2.0.1
Summary: Functional String Building
Home-page: UNKNOWN
Author: Perzan
Author-email: PerzanDevelopment@gmail.com
License: UNKNOWN
Platform: UNKNOWN
